noxus_sdk/__init__.py
noxus_sdk/__version__.py
noxus_sdk/client.py
noxus_sdk/schemas.py
noxus_sdk/cli/__init__.py
noxus_sdk/cli/main.py
noxus_sdk/cli/commands/__init__.py
noxus_sdk/cli/commands/plugin.py
noxus_sdk/integrations/__init__.py
noxus_sdk/integrations/base.py
noxus_sdk/integrations/nango.py
noxus_sdk/integrations/schemas.py
noxus_sdk/integrations/types.py
noxus_sdk/ncl/__init__.py
noxus_sdk/ncl/displays.py
noxus_sdk/ncl/outputs.py
noxus_sdk/ncl/parameters.py
noxus_sdk/ncl/rules.py
noxus_sdk/ncl/utils.py
noxus_sdk/nodes/__init__.py
noxus_sdk/nodes/base.py
noxus_sdk/nodes/connector.py
noxus_sdk/nodes/schemas.py
noxus_sdk/nodes/types.py
noxus_sdk/nodes/validation.py
noxus_sdk/plugins/__init__.py
noxus_sdk/plugins/base.py
noxus_sdk/plugins/context.py
noxus_sdk/plugins/create.py
noxus_sdk/plugins/exceptions.py
noxus_sdk/plugins/interfaces.py
noxus_sdk/plugins/manifest.py
noxus_sdk/plugins/package.py
noxus_sdk/plugins/serve.py
noxus_sdk/plugins/types.py
noxus_sdk/plugins/validate.py
noxus_sdk/plugins/sources/__init__.py
noxus_sdk/plugins/sources/git.py
noxus_sdk/plugins/sources/local.py
noxus_sdk/plugins/sources/marketplace.py
noxus_sdk/plugins/sources/upload.py
noxus_sdk/resources/__init__.py
noxus_sdk/resources/admin.py
noxus_sdk/resources/agentflows.py
noxus_sdk/resources/assistants.py
noxus_sdk/resources/base.py
noxus_sdk/resources/conversations.py
noxus_sdk/resources/files.py
noxus_sdk/resources/knowledge_bases.py
noxus_sdk/resources/runs.py
noxus_sdk/resources/workflows.py
noxus_sdk/templates/cookiecutter-plugin/cookiecutter.json
noxus_sdk/templates/cookiecutter-plugin/{{cookiecutter.__package_name}}/README.md
noxus_sdk/templates/cookiecutter-plugin/{{cookiecutter.__package_name}}/pyproject.toml
noxus_sdk/templates/cookiecutter-plugin/{{cookiecutter.__package_name}}/tests/__init__.py
noxus_sdk/templates/cookiecutter-plugin/{{cookiecutter.__package_name}}/{{cookiecutter.__package_name}}/__init__.py
noxus_sdk-0.1.0.dist-info/METADATA
noxus_sdk-0.1.0.dist-info/WHEEL
noxus_sdk-0.1.0.dist-info/entry_points.txt
noxus_sdk-0.1.0.dist-info/RECORD
