Metadata-Version: 2.4
Name: noxus-sdk
Version: 0.1.0
Summary: Software development kit to extend the Noxus platform
Author-email: Noxus Team <support@noxus.ai>
Keywords: development,noxus,plugin,sdk
Classifier: Programming Language :: Python
Classifier: Programming Language :: Python :: 3.10
Classifier: Programming Language :: Python :: 3.11
Classifier: Programming Language :: Python :: 3.12
Requires-Python: >=3.10
Requires-Dist: aiofiles
Requires-Dist: async-lru>=2.0.5
Requires-Dist: cookiecutter>=2.6.0
Requires-Dist: fastapi>=0.116.1
Requires-Dist: gitpython>=3.1.45
Requires-Dist: httpx-sse
Requires-Dist: httpx>=0.27.0
Requires-Dist: loguru>=0.7.0
Requires-Dist: markdownify>=1.1.0
Requires-Dist: pillow>=11.3.0
Requires-Dist: pydantic>=2.11.7
Requires-Dist: pyyaml>=6.0
Requires-Dist: ruff<1.0,>=0.6.3
Requires-Dist: semver>=3.0.4
Requires-Dist: typer[all]>=0.16.0
Requires-Dist: uvicorn>=0.35.0
